htmleval-0.1.0.dist-info/licenses/LICENSE
json/reviewJsonLib.py
json/compoundBlocks/column.py
json/compoundBlocks/interactive.py
json/compoundBlocks/tabs.py
json/simpleBlocks/multiRowChecked.py
json/simpleBlocks/multiRowOption.py
json/simpleBlocks/multiRowSelect.py
json/simpleBlocks/text.py
htmleval-0.1.0.dist-info/METADATA
htmleval-0.1.0.dist-info/WHEEL
htmleval-0.1.0.dist-info/top_level.txt
htmleval-0.1.0.dist-info/RECORD
