Metadata-Version: 2.4
Name: htmleval
Version: 0.1.0
Summary: A Python package that facilitates the creation of HTML evaluations.
Author: Markus Mobius
License: MIT License
Project-URL: Homepage, https://github.com/markusmobius/htmleval
Project-URL: Repository, https://github.com/markusmobius/htmleval
Project-URL: Bug Tracker, https://github.com/markusmobius/htmleval/issues
Keywords: html,evaluation,surveys,audits
Classifier: Development Status :: 3 - Alpha
Classifier: Intended Audience :: Developers
Classifier: License :: OSI Approved :: MIT License
Classifier: Operating System :: OS Independent
Classifier: Programming Language :: Python :: 3
Classifier: Programming Language :: Python :: 3.7
Classifier: Programming Language :: Python :: 3.8
Classifier: Programming Language :: Python :: 3.9
Classifier: Programming Language :: Python :: 3.10
Classifier: Programming Language :: Python :: 3.11
Classifier: Programming Language :: Python :: 3.12
Classifier: Programming Language :: Python :: 3.13
Requires-Python: >=3.7
License-File: LICENSE
Dynamic: license-file
